{
  "File": "Archivo",
  "Help": "Ayuda",
  "Yesterday": "Ayer",
  "Now": "Ahora",
  "%1h": "%1h",
  "Go": "Ir",
  "Edit": "Editar",
  "View": "Vista",
  "Window": "Ventana",
  "%1m": "%1min",
  "Incorrect Password": "Contraseña incorrecta",
  "Time Format": "Formato de hora",
  "Wallpaper": "Fondo de pantalla",
  "Yes": "Sí",
  "Default App": "Aplicación predeterminada",
  "Lockscreen": "Pantalla de bloqueo",
  "Activate Equora": "Activar Equora",
  "Avatar Size": "Tamaño del avatar",
  "Blur Lockscreen": "Desenfocar pantalla de bloqueo",
  "Off": "Apagado",
  "Set Color": "Establecer color",
  "Equora Settings": "Configuración de Equora",
  "Notch": "Notch",
  "Enable Wallpaper": "Activar fondo de pantalla",
  "Animation": "Animación",
  "Charging": "Cargando",
  "Search": "Buscar",
  "Auto hide": "Ocultar automáticamente",
  "Notifications": "Notificaciones",
  "Background color": "Color de fondo",
  "Scale": "Escala",
  "to Equora": "a Equora",
  "On": "Encendido",
  "Widgets": "Widgets",
  "User Note": "Nota del usuario",
  "(click to close)": "(clic para cerrar)",
  "Bubble": "Burbuja",
  "Location": "Ubicación",
  "Visual-Only mode": "Modo solo visual",
  "Date Format": "Formato de fecha",
  "No events today": "No hay eventos hoy",
  "Enter Password": "Ingresar contraseña",
  "Menu Bar": "Barra de menú",
  "Equora Account": "Cuenta de Equora",
  "Dialogs": "Diálogos",
  "Activation Key": "Clave de activación",
  "Width": "Ancho",
  "No network": "Sin red",
  "Enable Widgets": "Activar widgets",
  "Appearance": "Apariencia",
  "Enable Bar": "Activar barra",
  "Enable Lockscreen": "Activar pantalla de bloqueo",
  "Signature": "Firma",
  "Enable Launchpad": "Activar Launchpad",
  "Fade": "Desvanecer",
  "Osd": "OSD",
  "Remove": "Eliminar",
  "Tinted": "Teñido",
  "Welcome": "Bienvenido",
  "Custom Background": "Fondo personalizado",
  "Island mode": "Modo isla",
  "Remove all notifications": "Eliminar todas las notificaciones",
  "Wallpaper path": "Ruta del fondo de pantalla",
  "Launchpad": "Launchpad",
  "Enable Notch": "Activar Notch",
  "Go to Settings to activate your Account.": "Ve a Configuración para activar tu cuenta.",
  "Height": "Altura",
  "General": "General",
  "Enable OSD": "Activar OSD",
  "Nothing here yet :(": "Nada aquí todavía :(",
  "Enable Dialogs": "Activar diálogos",
  "No": "No",
  "Focus": "Enfoque",
  "Display": "Pantalla",
  "Volume": "Volumen",
  "Wi-Fi": "Wi-Fi",
  "Close": "Cerrar",
  "Language": "Idioma",
  "Edit Widgets": "Editar widgets",
  "Set Wallpaper": "Establecer fondo de pantalla",
  "Settings": "Configuración",
  "Remove Widget.": "Eliminar widget.",
  "Yellow": "Amarillo",
  "Clear": "Claro",
  "10 Seconds": "10 segundos",
  "Not Playing": "Nada en reproducción",
  "Orange": "Naranja",
  "Granite": "Granito",
  "Options": "Opciones",
  "Green": "Verde",
  "Icon & widget style": "Estilo de íconos y widgets",
  "5 Seconds": "5 segundos",
  "Light": "Claro",
  "Color": "Color",
  "Documents": "Documentos",
  "Remember Last Selection": "Recordar última selección",
  "+": "+",
  "Show Floating Thumbnail": "Mostrar miniatura flotante",
  "Sigrid is thinking…": "Sigrid está pensando…",
  "Theme": "Tema",
  "Dark": "Oscuro",
  "Save to": "Guardar en",
  "Default": "Predeterminado",
  "Blue": "Azul",
  "Purple": "Morado",
  "Error: Please try again later…": "Error: Inténtalo de nuevo más tarde…",
  "Clipboard": "Portapapeles",
  "Timer": "Temporizador",
  "Preview": "Vista previa",
  "Desktop": "Escritorio",
  "Use Appearance of Application": "Usar apariencia de la aplicación",
  "Dynamic": "Dinámico",
  "Show Mouse Pointer": "Mostrar puntero del mouse",
  "Ask Sigrid…": "Preguntar a Sigrid…",
  "Auto": "Automático",
  "Pink": "Rosa",
  "Red": "Rojo",
  "None": "Ninguno",
  "Search...": "Buscar..."
}